lynguine/.coverage
lynguine/__init__.py
lynguine/access/download.py
lynguine/access/io.py
lynguine/assess/compute.py
lynguine/assess/data.py
lynguine/clone_or_pull.py
lynguine/compute.py
lynguine/config/context.py
lynguine/config/defaults.yml
lynguine/config/interface.py
lynguine/convert.py
lynguine/coverage.xml
lynguine/log.py
lynguine/ndlappointment.py
lynguine/ndlcal.py
lynguine/ndlcgi.py
lynguine/ndlconvert.py
lynguine/ndlexpenses.py
lynguine/ndlimage.py
lynguine/ndlmarkdown.py
lynguine/ndlstrutil.py
lynguine/ndltext.py
lynguine/old_data.py
lynguine/replace_linguine.sh
lynguine/ruby/Gemfile
lynguine/ruby/json2yaml.rb
lynguine/test.xlsx
lynguine/tests/talk_tests.py
lynguine/tests/test.xlsx
lynguine/tests/test_access_download.py
lynguine/tests/test_access_io.py
lynguine/tests/test_assess_compute.py
lynguine/tests/test_assess_data.py
lynguine/tests/test_assess_data_compute.py
lynguine/tests/test_config_context.py
lynguine/tests/test_config_interface.py
lynguine/tests/test_customdataframe_integration.py
lynguine/tests/test_util_dataframe.py
lynguine/tests/test_util_files.py
lynguine/tests/test_util_liquid.py
lynguine/tests/test_util_misc.py
lynguine/tests/test_util_talk.py
lynguine/tests/test_util_tex.py
lynguine/tests/test_util_yaml.py
lynguine/util/.coverage
lynguine/util/dataframe.py
lynguine/util/fake.py
lynguine/util/files.py
lynguine/util/html.py
lynguine/util/liquid.py
lynguine/util/misc.py
lynguine/util/talk.py
lynguine/util/tex.py
lynguine/util/text.py
lynguine/util/yaml.py
lynguine-0.1.1.dist-info/METADATA
lynguine-0.1.1.dist-info/WHEEL
lynguine-0.1.1.dist-info/entry_points.txt
lynguine-0.1.1.dist-info/RECORD
