Metadata-Version: 2.1
Name: lynguine
Version: 0.1.1
Summary: Package for lynguine data oriented architecture interfaces.
Home-page: https://github.com/lawrennd/lynguine
License: MIT
Author: Neil D. Lawrence
Author-email: lawrennd@gmail.com
Requires-Python: >=3.11,<4.0
Classifier: License :: OSI Approved :: MIT License
Classifier: Programming Language :: Python
Classifier: Programming Language :: Python :: 3
Classifier: Programming Language :: Python :: 3.11
Classifier: Programming Language :: Python :: 3.12
Classifier: Programming Language :: Python :: Implementation :: PyPy
Requires-Dist: XlsxWriter
Requires-Dist: anyascii
Requires-Dist: bibtexparser
Requires-Dist: gitpython
Requires-Dist: google-api-python-client
Requires-Dist: google-auth-httplib2
Requires-Dist: gspread-pandas
Requires-Dist: markdown
Requires-Dist: markdownify
Requires-Dist: mimesis (>11)
Requires-Dist: numpy (>=1.0.0,<2.0.0)
Requires-Dist: openpyxl
Requires-Dist: pandas
Requires-Dist: pylatexenc
Requires-Dist: pyminizip
Requires-Dist: pypandoc
Requires-Dist: python-frontmatter
Requires-Dist: python-liquid
Requires-Dist: pyyaml
Requires-Dist: pyzmq (>=25.1.2,<26.0.0)
Requires-Dist: wget
